{
  "description": "Comparison between containers and Data Tag analysis for sGTM",
  "containers": [
    {
      "publicId": "GTM-MNRP4PF",
      "product": "GTM",
      "tagName": "messerattach.com",
      "aliases": [
        "GTM-MNRP4PF"
      ],
      "eventCount": 477,
      "uniqueEvents": [
        "gtm.click",
        "gtm.scrollDepth",
        "gtm.linkClick",
        null,
        "scroll",
        "form_start",
        "gtm.load",
        "gtm.dom",
        "cmplz_event_functional",
        "cmplz_event_preferences",
        "cmplz_event_marketing",
        "cmplz_event_statistics",
        "gtm.js",
        "begin_checkout",
        "checkout",
        "user_init",
        "gtm.init",
        "gtag.consent.update",
        "gtag.consent.default",
        "gtag.set",
        "gtm.init_consent",
        "form_submit",
        "view_cart",
        "view_item_list",
        "view_item",
        "add_to_cart"
      ],
      "tagsFired": [
        "FB - Page View",
        "google_ads_calls",
        "google_ads_800calls",
        "ms_uet_base",
        "Complianz.io - The Privacy Suite for WordPress",
        "Google Tag",
        "Conversion Linker",
        "Click Cease",
        "LinkedIn Insight",
        "Mailchimp",
        "ms_uet_view_item",
        "ms_uet_add_to_cart",
        "ms_uet_checkout"
      ],
      "errorCount": 0,
      "logCount": 30
    },
    {
      "publicId": "GT-NS9Z5FWG",
      "product": "GTAG",
      "tagName": "Messer Attachments",
      "aliases": [
        "GT-NS9Z5FWG",
        "GT-NMKXFNKR"
      ],
      "eventCount": 524,
      "uniqueEvents": [
        "gtm.click",
        "gtm.scrollDepth",
        "gtm.linkClick",
        null,
        "scroll",
        "form_start",
        "gtm.load",
        "gtm.dom",
        "cmplz_event_functional",
        "cmplz_event_preferences",
        "cmplz_event_marketing",
        "cmplz_event_statistics",
        "gtm.js",
        "begin_checkout",
        "checkout",
        "user_init",
        "gtag.config",
        "gtm.init",
        "gtag.consent.update",
        "gtag.consent.default",
        "gtag.set",
        "gtm.init_consent",
        "User Engagement",
        "form_submit",
        "view_cart",
        "view_item_list",
        "view_item",
        "add_to_cart"
      ],
      "tagsFired": [
        "_Product-Owned Activity Tag 39",
        "_Product-Owned Activity Tag 37",
        "_Product-Owned Activity Tag 36",
        "_Product-Owned Activity Tag 35",
        "_Product-Owned Activity Tag 34",
        "_Product-Owned Activity Tag 33"
      ],
      "errorCount": 0,
      "logCount": 0
    }
  ],
  "gaps": [
    {
      "issue": "NO_DATA_TAG",
      "impact": "This event is NOT sent to sGTM"
    },
    {
      "event": "gtag.consent.update",
      "issue": "NO_DATA_TAG",
      "impact": "This event is NOT sent to sGTM"
    },
    {
      "event": "gtag.consent.default",
      "issue": "NO_DATA_TAG",
      "impact": "This event is NOT sent to sGTM"
    },
    {
      "event": "gtag.set",
      "issue": "NO_DATA_TAG",
      "impact": "This event is NOT sent to sGTM"
    }
  ],
  "dataTagAnalysis": {
    "description": "Data Tag sends events from wGTM to sGTM. Events NOT in this list are NOT sent to server.",
    "totalFirings": 304,
    "eventsWithDataTag": [
      "gtm.click",
      "gtm.scrollDepth",
      "gtm.linkClick",
      "scroll",
      "form_start",
      "gtm.load",
      "gtm.dom",
      "cmplz_event_functional",
      "cmplz_event_preferences",
      "cmplz_event_marketing",
      "cmplz_event_statistics",
      "begin_checkout",
      "checkout",
      "user_init",
      "gtm.js",
      "gtm.init",
      "gtm.init_consent",
      "form_submit",
      "view_cart",
      "view_item_list",
      "view_item",
      "add_to_cart"
    ],
    "eventsWITHOUT_DataTag": [
      null,
      "gtag.consent.update",
      "gtag.consent.default",
      "gtag.set"
    ]
  }
}